behind_api_client/__init__.py
behind_api_client/behind_api_client.py
behind_api_client/chat/__init__.py
behind_api_client/chat/chat_app.py
behind_api_client/chat/chat_v10.py
behind_api_client/chat/chat_v10_chat.py
behind_api_client/chat/chat_v10_chats.py
behind_api_client/chat/chat_v10_message.py
behind_api_client/chat/chat_v20.py
behind_api_client/chat/chat_v20_chat.py
behind_api_client/chat/chat_v20_message.py
behind_api_client/easyjob/__init__.py
behind_api_client/easyjob/easyjob_app.py
behind_api_client/easyjob/easyjob_v10.py
behind_api_client/easyjob/easyjob_v10_answers.py
behind_api_client/easyjob/easyjob_v10_applicants.py
behind_api_client/easyjob/easyjob_v10_applications.py
behind_api_client/easyjob/easyjob_v10_candidate_profile_artifacts.py
behind_api_client/easyjob/easyjob_v10_candidate_profiles.py
behind_api_client/easyjob/easyjob_v10_companies.py
behind_api_client/easyjob/easyjob_v10_cv.py
behind_api_client/easyjob/easyjob_v10_departments.py
behind_api_client/easyjob/easyjob_v10_job_description_artifacts.py
behind_api_client/easyjob/easyjob_v10_job_description_candidate_questions.py
behind_api_client/easyjob/easyjob_v10_job_descriptions.py
behind_api_client/easyjob/easyjob_v10_reports.py
behind_api_client/globals/__init__.py
behind_api_client/globals/globals_app.py
behind_api_client/globals/globals_v10.py
behind_api_client/globals/globals_v10_sockets.py
behind_api_client/globals/globals_v10_storage.py
behind_api_client/gpt/__init__.py
behind_api_client/gpt/gpt_app.py
behind_api_client/gpt/gpt_v10.py
behind_api_client/gpt/gpt_v10_prompt.py
behind_api_client/gpt/gpt_v10_request.py
behind_api_client/gpt/gpt_v10_storedprompts.py
behind_api_client/gpt/gpt_v10_whisper.py
behind_api_client/gpt/gpt_v20.py
behind_api_client/gpt/gpt_v20_prompt.py
behind_api_client/gpt/gpt_v30.py
behind_api_client/gpt/gpt_v30_chat.py
behind_api_client/gpt/gpt_v30_prompt.py
behind_api_client/gpt/gpt_v30_prompts.py
behind_api_client/gpt/gpt_v40.py
behind_api_client-1.0.668.dist-info/licenses/LICENSE
behind_api_client-1.0.668.dist-info/METADATA
behind_api_client-1.0.668.dist-info/WHEEL
behind_api_client-1.0.668.dist-info/top_level.txt
behind_api_client-1.0.668.dist-info/RECORD
